pylukeroberts/__init__.py
pylukeroberts/const.py
pylukeroberts/pylukeroberts.py
pylukeroberts-0.4.0.dist-info/LICENSE.txt
pylukeroberts-0.4.0.dist-info/METADATA
pylukeroberts-0.4.0.dist-info/WHEEL
pylukeroberts-0.4.0.dist-info/RECORD
