Metadata-Version: 2.3
Name: pylukeroberts
Version: 0.4.0
Summary: A library to control Luke Roberts lamps via Bluetooth Low Energy
Keywords: bluetooth,BLE,luvo,control,Luke Roberts
Author: Timur Pulathaneli
Author-email: timur@koeln.de
Requires-Python: >=3.10,<3.14
Classifier: Programming Language :: Python :: 3
Classifier: Programming Language :: Python :: 3.10
Classifier: Programming Language :: Python :: 3.11
Classifier: Programming Language :: Python :: 3.12
Classifier: Programming Language :: Python :: 3.13
Requires-Dist: bleak (>=2.1.1)
